replicate_nano_banana_mcp/__init__.py
replicate_nano_banana_mcp/cli.py
replicate_nano_banana_mcp/py.typed
replicate_nano_banana_mcp/server.py
replicate_nano_banana_mcp-0.1.0.dist-info/METADATA
replicate_nano_banana_mcp-0.1.0.dist-info/WHEEL
replicate_nano_banana_mcp-0.1.0.dist-info/entry_points.txt
replicate_nano_banana_mcp-0.1.0.dist-info/licenses/LICENSE
replicate_nano_banana_mcp-0.1.0.dist-info/RECORD
