Metadata-Version: 2.4
Name: replicate-nano-banana-mcp
Version: 0.1.0
Summary: MCP server for generating images using Google's Nano Banana Pro model via Replicate
Project-URL: Homepage, https://github.com/sugarforever/replicate-nano-banana-mcp
Project-URL: Repository, https://github.com/sugarforever/replicate-nano-banana-mcp
Author-email: sugarforever <william.1022@gmail.com>
License-File: LICENSE
Keywords: ai,image-generation,mcp,nano-banana,replicate
Classifier: Development Status :: 4 - Beta
Classifier: Intended Audience :: Developers
Classifier: License :: OSI Approved :: MIT License
Classifier: Programming Language :: Python :: 3
Classifier: Programming Language :: Python :: 3.12
Classifier: Programming Language :: Python :: 3.13
Requires-Python: >=3.12
Requires-Dist: mcp>=1.0.0
Requires-Dist: replicate>=1.0.0
